pyre_extensions/__init__.py
pyre_extensions/generic.py
pyre_extensions/refinement.py
pyre_extensions/safe_json.py
pyre_extensions/type_variable_operators.py
pyre_extensions/tests/__init__.py
pyre_extensions/tests/basic_test.py
pyre_extensions/tests/safe_json_test.py
pyre_extensions-0.0.30.dist-info/LICENSE
pyre_extensions-0.0.30.dist-info/METADATA
pyre_extensions-0.0.30.dist-info/WHEEL
pyre_extensions-0.0.30.dist-info/top_level.txt
pyre_extensions-0.0.30.dist-info/RECORD
