Metadata-Version: 2.1
Name: pyre-extensions
Version: 0.0.30
Summary: Type system extensions for use with the pyre type checker
Home-page: https://pyre-check.org
Author: Facebook
Author-email: pyre@fb.com
Classifier: Development Status :: 3 - Alpha
Classifier: Environment :: Console
Classifier: Intended Audience :: Developers
Classifier: License :: OSI Approved :: MIT License
Classifier: Programming Language :: Python
Classifier: Topic :: Software Development
Classifier: Operating System :: OS Independent
Classifier: Typing :: Typed
License-File: LICENSE
Requires-Dist: typing-inspect
Requires-Dist: typing-extensions
